energat/__init__.py
energat/__main__.py
energat/basepower.py
energat/common.py
energat/target.py
energat/tracer.py
energat-1.0.6.dist-info/entry_points.txt
energat-1.0.6.dist-info/LICENSE
energat-1.0.6.dist-info/WHEEL
energat-1.0.6.dist-info/METADATA
energat-1.0.6.dist-info/RECORD
