Metadata-Version: 2.1
Name: energat
Version: 1.0.6
Summary: EnergAt: A software energy attribution tool.
Author-email: Hongyu Hè <honghe@inf.ethz.ch>
Requires-Python: >=3.10
Classifier: Topic :: System :: Monitoring
Classifier: Topic :: System :: Operating System
Classifier: Topic :: System :: Power (UPS)
Classifier: Topic :: System :: Operating System Kernels :: Linux
Classifier: Programming Language :: Python :: 3
Requires-Dist: absl-py
Requires-Dist: contextlib2
Requires-Dist: ml-collections
Requires-Dist: numpy
Requires-Dist: pandas
Requires-Dist: psutil
Requires-Dist: python-dateutil
Requires-Dist: pytz
Requires-Dist: PyYAML
Requires-Dist: six
Requires-Dist: tzdata
Requires-Dist: pytest ; extra == "test"
Requires-Dist: mypy ; extra == "test"
Requires-Dist: flake8 ; extra == "test"
Project-URL: Paper, https://hongyu.nl/papers/2023_hotcarbon_energat.pdf
Project-URL: Source, https://github.com/HongyuHe/energat
Provides-Extra: test
